qubrid/__init__.py
qubrid-1.0.dist-info/METADATA
qubrid-1.0.dist-info/WHEEL
qubrid-1.0.dist-info/top_level.txt
qubrid-1.0.dist-info/RECORD
